exco/__init__.py
exco/__version__.py
exco/cell_full_path.py
exco/cell_location.py
exco/dereferator.py
exco/excel_extraction_scope.py
exco/exception.py
exco/setting.py
exco/sheet_name_alias.py
exco/shortcut.py
exco/util.py
exco/exco_template/__init__.py
exco/exco_template/exco_block.py
exco/exco_template/exco_template.py
exco/exco_watch/__init__.py
exco/extractor/__init__.py
exco/extractor/actor.py
exco/extractor/base_factory.py
exco/extractor/cell_extraction_task.py
exco/extractor/excel_processor.py
exco/extractor/table_extraction_task.py
exco/extractor/assumption/__init__.py
exco/extractor/assumption/assumption.py
exco/extractor/assumption/assumption_factory.py
exco/extractor/assumption/assumption_result.py
exco/extractor/assumption/built_in/__init__.py
exco/extractor/assumption/built_in/left_cell_match_assumption.py
exco/extractor/locator/__init__.py
exco/extractor/locator/locating_result.py
exco/extractor/locator/locator.py
exco/extractor/locator/locator_factory.py
exco/extractor/locator/built_in/__init__.py
exco/extractor/locator/built_in/at_comment_cell_locator.py
exco/extractor/locator/built_in/below_of_locator.py
exco/extractor/locator/built_in/below_of_regex_locator.py
exco/extractor/locator/built_in/right_of_locator.py
exco/extractor/locator/built_in/right_of_regex_locator.py
exco/extractor/locator/built_in/search_below_of_locator.py
exco/extractor/locator/built_in/search_right_of_locator.py
exco/extractor/locator/built_in/within_locator.py
exco/extractor/parser/__init__.py
exco/extractor/parser/parser.py
exco/extractor/parser/parser_factory.py
exco/extractor/parser/parsing_result.py
exco/extractor/parser/built_in/__init__.py
exco/extractor/parser/built_in/date_parser.py
exco/extractor/parser/built_in/float_parser.py
exco/extractor/parser/built_in/int_parser.py
exco/extractor/parser/built_in/link_parser.py
exco/extractor/parser/built_in/string_parser.py
exco/extractor/parser/built_in/value_parser.py
exco/extractor/table_end_conditions/__init__.py
exco-0.2.9.dist-info/LICENSE
exco-0.2.9.dist-info/METADATA
exco-0.2.9.dist-info/WHEEL
exco-0.2.9.dist-info/entry_points.txt
exco-0.2.9.dist-info/top_level.txt
exco-0.2.9.dist-info/RECORD
