Metadata-Version: 2.1
Name: exco
Version: 0.2.9
Summary: Excel Comment Orm
Home-page: https://github.com/thegangtechnology/exco
Author: Piti Ongmongkolkul
Author-email: piti118@gmail.com
License: Private
Classifier: 
License-File: LICENSE
Requires-Dist: openpyxl
Requires-Dist: pyyaml
Requires-Dist: stringcase
Requires-Dist: watchdog
Provides-Extra: dev
Requires-Dist: ipykernel ; extra == 'dev'
Requires-Dist: mypy ; extra == 'dev'
Requires-Dist: autopep8 ; extra == 'dev'
Requires-Dist: pytest ; extra == 'dev'
Requires-Dist: pytest-cov ; extra == 'dev'
Requires-Dist: wheel ; extra == 'dev'
Requires-Dist: flake8 ; extra == 'dev'
Provides-Extra: test
Requires-Dist: pytest ; extra == 'test'
Requires-Dist: pytest-cov ; extra == 'test'
Requires-Dist: flake8 ; extra == 'test'
